Metadata-Version: 1.0
Name: udmlprob-distributions
Version: 0.1
Summary: Gaussian and Binomial Distributions
Home-page: UNKNOWN
Author: Ikenna Nwosu
Author-email: ikenna.nwosu@kositechconsultingltd.com
License: UNKNOWN
Platform: UNKNOWN
